Workbook

Sheet Sheet1
A1: Area Code | B1: Product | C1: Product Type | D1: State | E1: Territory | F1: Target Profit | G1: Profit | H1: Marked Price
A2: 970 | B2: Decaf Irish Cream | C2: =VLOOKUP(B2,Sheet2!$A$2:$B$14,2) -> Coffee | D2: Colorado | E2: Central | F2: 110 | G2: 101 | H2: 234 | J2: lookup function
A3: 309 | B3: Decaf Irish Cream | C3: =VLOOKUP(B3,Sheet2!$A$2:$B$14,2) -> Coffee | D3: Illinois | E3: Central | F3: 100 | G3: 87 | H3: 234 | J3: #=vlookp()
A4: 614 | B4: Decaf Irish Cream | C4: =VLOOKUP(B4,Sheet2!$A$2:$B$14,2) -> Coffee | D4: Ohio | E4: Central | F4: 20 | G4: 0 | H4: 150
A5: 754 | B5: Decaf Irish Cream | C5: =VLOOKUP(B5,Sheet2!$A$2:$B$14,2) -> Coffee | D5: Florida | E5: East | F5: 70 | G5: 67 | H5: 200
A6: 325 | B6: Decaf Irish Cream | C6: =VLOOKUP(B6,Sheet2!$A$2:$B$14,2) -> Coffee | D6: Texas | E6: South | F6: 100 | G6: 68 | H6: 190
A7: 650 | B7: Decaf Irish Cream | C7: =VLOOKUP(B7,Sheet2!$A$2:$B$14,2) -> Coffee | D7: California | E7: West | F7: 120 | G7: 117 | H7: 118
A8: 720 | B8: Decaf Espresso | C8: =VLOOKUP(B8,Sheet2!$A$2:$B$14,2) -> Espresso | D8: Colorado | E8: Central | F8: 80 | G8: 53 | H8: 180
A9: 630 | B9: Decaf Espresso | C9: =VLOOKUP(B9,Sheet2!$A$2:$B$14,2) -> Espresso | D9: Illinois | E9: Central | F9: 180 | G9: 140 | H9: 456
A10: 614 | B10: Decaf Espresso | C10: =VLOOKUP(B10,Sheet2!$A$2:$B$14,2) -> Espresso | D10: Ohio | E10: Central | F10: 40 | G10: 16 | H10: 130
A11: 754 | B11: Decaf Espresso | C11: =VLOOKUP(B11,Sheet2!$A$2:$B$14,2) -> Espresso | D11: Florida | E11: East | F11: 60 | G11: 50 | H11: 180
A12: 956 | B12: Decaf Espresso | C12: =VLOOKUP(B12,Sheet2!$A$2:$B$14,2) -> Espresso | D12: Texas | E12: South | F12: 60 | G12: 54 | H12: 134
A13: 213 | B13: Decaf Espresso | C13: =VLOOKUP(B13,Sheet2!$A$2:$B$14,2) -> Espresso | D13: California | E13: West | F13: 200 | G13: 203 | H13: 546
A14: 719 | B14: Amaretto | C14: =VLOOKUP(B14,Sheet2!$A$2:$B$14,2) -> Coffee | D14: Colorado | E14: Central | F14: 100 | G14: 94 | H14: 219
A15: 740 | B15: Amaretto | C15: =VLOOKUP(B15,Sheet2!$A$2:$B$14,2) -> Coffee | D15: Ohio | E15: Central | F15: 50 | G15: 34 | H15: 140
... A101: 970 | B101: Mint | C101: =VLOOKUP(B101,Sheet2!$A$2:$B$14,2) -> Herbal Tea | D101: Colorado | E101: Central | F101: 40 | G101: 33 | H101: 140

Sheet Sheet2
A1: Product | B1: Product Type
A2: Amaretto | B2: Coffee
A3: Caffe Latte | B3: Espresso | D3: Chamomile
A4: Caffe Mocha | B4: Espresso | D4: =VLOOKUP(D3,A2:B14,2) -> Herbal Tea
A5: Chamomile | B5: Herbal Tea
A6: Colombian | B6: Coffee
A7: Darjeeling | B7: Tea
A8: Decaf Espresso | B8: Espresso
A9: Decaf Irish Cream | B9: Coffee
A10: Earl Grey | B10: Tea
A11: Green Tea | B11: Tea
A12: Lemon | B12: Herbal Tea
A13: Mint | B13: Herbal Tea
A14: Regular Espresso | B14: Espresso

Sheet Sheet3
C2: Selling Price | E2: TAX Rate
C3: Lower End | D3: Higher End | E3: VAT
C4: 1001 | D4: 2000 | E4: 0.05
C5: 2001 | D5: 5000 | E5: 0.1
C6: 5001 | D6: 10000 | E6: 0.2
C7: 10001 | D7: above | E7: 0.3
C12: Selling Price | D12: Tax
C13: 1500 | D13: =VLOOKUP(C13,$C$3:$E$7,3) -> 0.05
C14: 2500 | D14: =VLOOKUP(C14,$C$3:$E$7,3) -> 0.1
C15: 20000 | D15: =VLOOKUP(C15,$C$3:$E$7,3) -> 0.3
C16: 10000 | D16: =VLOOKUP(C16,$C$3:$E$7,3) -> 0.2

Sheet Sheet4
A1: Order ID | B1: Customer Name | C1: Profit | D1: Sales
A2: CA-2019-100867 | B2: Eugene Hildebrand | C2: 9 | D2: 33
A3: CA-2019-107153 | B3: George Zrebassa | C3: 4 | D3: 11
A4: CA-2019-115238 | B4: Jane Waco | C4: 89 | D4: 281
A5: CA-2019-115777 | B5: Doug O'Connell | C5: 182 | D5: 388
A6: CA-2019-117964 | B6: Michael Knudson | C6: -19 | D6: 56
A7: CA-2019-119508 | B7: Tracy Zic | C7: 15 | D7: 42
A8: CA-2019-123625 | B8: Bruce Galang | C8: 88 | D8: 258
A9: CA-2019-123664 | B9: Neil Cohen | C9: -25 | D9: 58
A10: CA-2019-125388 | B10: Michael Paige | C10: 26 | D10: 174
A11: CA-2019-126438 | B11: Alex Russell | C11: 4 | D11: 15
A12: CA-2019-126634 | B12: Alan Barnes | C12: 40 | D12: 94
A13: CA-2019-129322 | B13: Denny Blanton | C13: 255 | D13: 601
... A103: CA-2022-192314 | B103: Jennifer Sheldon | C103: 4 | D103: 10

Sheet Sheet5
C2: Order ID | D2: Customer Name | E2: Profit
C3: CA-2019-100867 | D3: =VLOOKUP(C3,Sheet4!$A$2:$D$103,2) -> Eugene Hildebrand | E3: =VLOOKUP(C3,Sheet4!$A$2:$D$103,3) -> 9
C4: CA-2019-126634 | D4: =VLOOKUP(C4,Sheet4!$A$2:$D$103,2) -> Alan Barnes | E4: =VLOOKUP(C4,Sheet4!$A$2:$D$103,3) -> 40
C5: CA-2019-152443 | D5: =VLOOKUP(C5,Sheet4!$A$2:$D$103,2) -> Frank Gastineau | E5: =VLOOKUP(C5,Sheet4!$A$2:$D$103,3) -> 297
C6: CA-2019-160325 | D6: =VLOOKUP(C6,Sheet4!$A$2:$D$103,2) -> Bart Pistole | E6: =VLOOKUP(C6,Sheet4!$A$2:$D$103,3) -> 241
C7: CA-2020-145154 | D7: =VLOOKUP(C7,Sheet4!$A$2:$D$103,2) -> Michael Knudson | E7: =VLOOKUP(C7,Sheet4!$A$2:$D$103,3) -> -21
C8: CA-2020-111111 | D8: =VLOOKUP(C8,Sheet4!$A$2:$D$103,2) -> Neil Cohen | E8: =VLOOKUP(C8,Sheet4!$A$2:$D$103,3) -> 23
C9: CA-2020-152681 | D9: =VLOOKUP(C9,Sheet4!$A$2:$D$103,2) -> Scott Cohen | E9: =VLOOKUP(C9,Sheet4!$A$2:$D$103,3) -> 2

Sheet Sheet6
A1: Order ID | B1: CA-2019-100867 | C1: CA-2019-107153 | D1: CA-2019-115238 | E1: CA-2019-115777 | F1: CA-2019-117964 | G1: CA-2019-119508 | H1: CA-2019-123625 | I1: CA-2019-123664 | J1: CA-2019-125388 | K1: CA-2019-126438 | L1: CA-2019-126634 | M1: CA-2019-129322 | N1: CA-2019-131807 | O1: CA-2019-132339 | P1: CA-2019-139675 | Q1: CA-2019-141531 | R1: CA-2019-143500 | S1: CA-2019-146626 | T1: CA-2019-151799 | U1: CA-2019-152443 | V1: CA-2019-153623 | W1: CA-2019-153738 | X1: CA-2019-160325 | Y1: CA-2019-166086 | Z1: CA-2019-166695 | AA1: CA-2019-184712 | AB1: CA-2020-112224 | AC1: CA-2020-115238 | AD1: CA-2020-119508 | AE1: CA-2020-129322 | AF1: CA-2020-132548 | AG1: CA-2020-139675 | AH1: CA-2020-145154 | AI1: CA-2020-150547 | AJ1: CA-2020-152681 | AK1: CA-2020-153071 | AL1: CA-2020-153738 | AM1: CA-2020-154124 | AN1: CA-2020-154231 | AO1: CA-2020-155586 | AP1: CA-2020-158792 | AQ1: CA-2021-108735 | AR1: CA-2021-111254 | AS1: CA-2021-112109 | AT1: CA-2021-115238 | AU1: CA-2021-115483 | AV1: CA-2021-119508 | AW1: CA-2021-121465 | AX1: CA-2021-124574 | AY1: CA-2021-124626 | AZ1: CA-2021-125724 | BA1: CA-2021-126627 | BB1: CA-2021-129322 | BC1: CA-2021-133541 | BD1: CA-2021-135480 | BE1: CA-2021-136547 | BF1: CA-2021-139675 | BG1: CA-2021-141082 | BH1: CA-2021-153738 | BI1: CA-2021-155412 | BJ1: CA-2021-155586 | BK1: CA-2021-158792 | BL1: CA-2021-169856 | BM1: CA-2021-174514 | BN1: CA-2021-187423 | BO1: CA-2021-192314 | BP1: CA-2022-105471 | BQ1: CA-2022-106541 | BR1: CA-2022-107004 | BS1: CA-2022-108735 | BT1: CA-2022-112109 | BU1: CA-2022-115238 | BV1: CA-2022-115483 | BW1: CA-2022-115777 | BX1: CA-2022-119508 | BY1: CA-2022-121451 | BZ1: CA-2022-124626 | CA1: CA-2022-125388 | CB1: CA-2022-125724 | CC1: CA-2022-126438 | CD1: CA-2022-126627 | CE1: CA-2022-126634 | CF1: CA-2022-129322 | CG1: CA-2022-130494 | CH1: CA-2022-131807 | CI1: CA-2022-132339 | CJ1: CA-2022-135471 | CK1: CA-2022-135480 | CL1: CA-2022-139675 | CM1: CA-2022-141082 | CN1: CA-2022-141531 | CO1: CA-2022-143500 | CP1: CA-2022-145612 | CQ1: CA-2022-146626 | CR1: CA-2022-151799 | CS1: CA-2022-153738 | CT1: CA-2022-154121 | CU1: CA-2022-158740 | CV1: CA-2022-160325 | CW1: CA-2022-166695 | CX1: CA-2022-184712 | CY1: CA-2022-192314
A2: Customer Name | B2: Eugene Hildebrand | C2: George Zrebassa | D2: Jane Waco | E2: Doug O'Connell | F2: Michael Knudson | G2: Tracy Zic | H2: Bruce Galang | I2: Neil Cohen | J2: Michael Paige | K2: Alex Russell | L2: Alan Barnes | M2: Denny Blanton | N2: Greg Guthrie | O2: Jennifer Braxton | P2: Nicole Fjeld | Q2: Bruce Galang | R2: Harry Olson | S2: James Peterman | T2: Ben Ferrer | U2: Frank Gastineau | V2: James Peterman | W2: Alejandro Grove | X2: Bart Pistole | Y2: Carol Triggs | Z2: Chuck Clark | AA2: Neil Cohen | AB2: Neil Cohen | AC2: Jane Waco | AD2: Tracy Zic | AE2: Denny Blanton | AF2: Carol Triggs | AG2: Nicole Fjeld | AH2: Michael Knudson | AI2: Frank Gastineau | AJ2: Scott Cohen | AK2: George Zrebassa | AL2: Alejandro Grove | AM2: Michael Knudson | AN2: Eugene Hildebrand | AO2: Xylona Preis | AP2: Brian Dahlen | AQ2: Jessica Myrick | AR2: Michael Knudson | AS2: Joe Elijah | AT2: Jane Waco | AU2: Jill Trafton | AV2: Tracy Zic | AW2: Harry Olson | AX2: Michael Knudson | AY2: James Peterman | AZ2: Suzanne McNair | BA2: William Brown | BB2: Denny Blanton | BC2: Neil Cohen | BD2: Bruce Galang | BE2: Frank Gastineau | BF2: Nicole Fjeld | BG2: Fred McMath | BH2: Alejandro Grove | BI2: Scott Cohen | BJ2: Xylona Preis | BK2: Brian Dahlen | BL2: Carol Triggs | BM2: Eugene Hildebrand | BN2: George Zrebassa | BO2: Jennifer Sheldon | BP2: Neil Cohen | BQ2: Michael Knudson | BR2: Eugene Hildebrand | BS2: Jessica Myrick | BT2: Joe Elijah | BU2: Jane Waco | BV2: Jill Trafton | BW2: Doug O'Connell | BX2: Tracy Zic | BY2: Scott Cohen | BZ2: James Peterman | CA2: Michael Paige | CB2: Suzanne McNair | CC2: Alex Russell | CD2: William Brown | CE2: Alan Barnes | CF2: Denny Blanton | CG2: Harry Olson | CH2: Greg Guthrie | CI2: Jennifer Braxton | CJ2: George Zrebassa | CK2: Bruce Galang | CL2: Nicole Fjeld | CM2: Fred McMath | CN2: Bruce Galang | CO2: Harry Olson | CP2: Michael Knudson | CQ2: James Peterman | CR2: Ben Ferrer | CS2: Alejandro Grove | CT2: Scott Cohen | CU2: Frank Gastineau | CV2: Bart Pistole | CW2: Chuck Clark | CX2: Neil Cohen | CY2: Jennifer Sheldon
A3: Profit | B3: 9 | C3: 4 | D3: 89 | E3: 182 | F3: -19 | G3: 15 | H3: 88 | I3: -25 | J3: 26 | K3: 4 | L3: 40 | M3: 255 | N3: -14 | O3: 9 | P3: 195 | Q3: 30 | R3: -1 | S3: 10 | T3: 432 | U3: 297 | V3: 71 | W3: 17 | X3: 241 | Y3: 216 | Z3: -55 | AA3: 23 | AB3: -25 | AC3: 89 | AD3: 79 | AE3: 16 | AF3: 9 | AG3: 195 | AH3: -21 | AI3: 4 | AJ3: 2 | AK3: 2 | AL3: 9 | AM3: 2 | AN3: 1 | AO3: 30 | AP3: 10 | AQ3: 14 | AR3: 2 | AS3: 127 | AT3: 89 | AU3: -99 | AV3: 15 | AW3: 165 | AX3: -21 | AY3: 35 | AZ3: 20 | BA3: 11 | BB3: 255 | BC3: -25 | BD3: 30 | BE3: -6 | BF3: 195 | BG3: -31 | BH3: 17 | BI3: 2 | BJ3: 24 | BK3: 10 | BL3: 15 | BM3: 3 | BN3: 17 | BO3: 4 | BP3: -25 | BQ3: -21 | BR3: 9 | BS3: 24 | BT3: 54 | BU3: 89 | BV3: -99 | BW3: 182 | BX3: 15 | BY3: 2 | BZ3: 35 | CA3: 2 | CB3: 9 | CC3: 1 | CD3: -33 | CE3: 2 | CF3: 255 | CG3: 165 | CH3: 1417 | CI3: 9 | CJ3: 9 | CK3: 30 | CL3: 195 | CM3: 58 | CN3: 30 | CO3: -1 | CP3: 2 | CQ3: 35 | CR3: 10 | CS3: 17 | CT3: 2 | CU3: 3 | CV3: 28 | CW3: -55 | CX3: 23 | CY3: 4
A4: Sales | B4: 33 | C4: 11 | D4: 281 | E4: 388 | F4: 56 | G4: 42 | H4: 258 | I4: 58 | J4: 174 | K4: 15 | L4: 94 | M4: 601 | N4: 753 | O4: 19 | P4: 1243 | Q4: 88 | R4: 3 | S4: 20 | T4: 1843 | U4: 712 | V4: 198 | W4: 38 | X4: 830 | Y4: 1091 | Z4: 868 | AA4: 74 | AB4: 58 | AC4: 281 | AD4: 402 | AE4: 159 | AF4: 115 | AG4: 1243 | AH4: 40 | AI4: 9 | AJ4: 7 | AK4: 7 | AL4: 24 | AM4: 16 | AN4: 2 | AO4: 74 | AP4: 22 | AQ4: 79 | AR4: 16 | AS4: 1039 | AT4: 281 | AU4: 72 | AV4: 42 | AW4: 541 | AX4: 40 | AY4: 99 | AZ4: 64 | BA4: 137 | BB4: 601 | BC4: 58 | BD4: 88 | BE4: 14 | BF4: 1243 | BG4: 83 | BH4: 38 | BI4: 7 | BJ4: 54 | BK4: 22 | BL4: 55 | BM4: 6 | BN4: 38 | BO4: 10 | BP4: 58 | BQ4: 40 | BR4: 19 | BS4: 258 | BT4: 725 | BU4: 281 | BV4: 72 | BW4: 388 | BX4: 42 | BY4: 7 | BZ4: 99 | CA4: 41 | CB4: 68 | CC4: 3 | CD4: 30 | CE4: 7 | CF4: 601 | CG4: 541 | CH4: 5607 | CI4: 19 | CJ4: 19 | CK4: 88 | CL4: 1243 | CM4: 126 | CN4: 88 | CO4: 3 | CP4: 16 | CQ4: 99 | CR4: 679 | CS4: 38 | CT4: 7 | CU4: 6 | CV4: 79 | CW4: 868 | CX4: 74 | CY4: 10
F7: Michael Knudson
F9: =HLOOKUP(F7,B2:K4,3) -> 56

Sheet Sheet7
C6: Order ID | D6: Customer Name | E6: Profit
C7: CA-2019-100867 | D7: =HLOOKUP(C7,Sheet6!$B$1:$DA$4,2) -> Eugene Hildebrand | E7: =HLOOKUP(C7,Sheet6!$B$1:$DA$4,3) -> 9
C8: CA-2019-126634 | D8: =HLOOKUP(C8,Sheet6!$B$1:$DA$4,2) -> Alan Barnes | E8: =HLOOKUP(C8,Sheet6!$B$1:$DA$4,3) -> 40
C9: CA-2019-152443 | D9: =HLOOKUP(C9,Sheet6!$B$1:$DA$4,2) -> Frank Gastineau | E9: =HLOOKUP(C9,Sheet6!$B$1:$DA$4,3) -> 297
C10: CA-2019-160325 | D10: =HLOOKUP(C10,Sheet6!$B$1:$DA$4,2) -> Bart Pistole | E10: =HLOOKUP(C10,Sheet6!$B$1:$DA$4,3) -> 241
C11: CA-2020-145154 | D11: =HLOOKUP(C11,Sheet6!$B$1:$DA$4,2) -> Michael Knudson | E11: =HLOOKUP(C11,Sheet6!$B$1:$DA$4,3) -> -21
C12: CA-2020-111111 | D12: =HLOOKUP(C12,Sheet6!$B$1:$DA$4,2) -> Neil Cohen | E12: =HLOOKUP(C12,Sheet6!$B$1:$DA$4,3) -> 23
C13: CA-2020-152681 | D13: =HLOOKUP(C13,Sheet6!$B$1:$DA$4,2) -> Scott Cohen | E13: =HLOOKUP(C13,Sheet6!$B$1:$DA$4,3) -> 2
